{
  "Argentina": [0, 1, 12],
  "Brazil": [2, 2, 7],
  "Canada": [2, 3, 5],
  "Chile": [0,0,1],
  "Colombia": [0,1, 0],
  "Cuba":[0,0,1],
  "Mexico": [0,1,2],
  "United States": [21, 36, 40],
  "Egypt": [0,0,15],
  "Iran": [4,2,6],
  "Iraq": [0, 1, 4],
  "Israel": [1, 0 ,0],
  "Jordan": [0, 3, 0],
  "Lebanon": [0,0,5],
  "Palestine": [0, 7, 0],
  "Syria": [0, 1, 7],
  "Turkiye": [0, 9, 16],
  "United Arab Emirates": [3, 0 ,0],
  "Armenia": [1,0,0],
  "Cambodia": [1, 2, 0],
  "China": [2, 1,5],
  "Georgia": [0,0,2],
  "India": [0, 32, 26],
  "Indonesia": [0, 3, 5],
  "Japan": [0,0,1],
  "Philippines": [4, 7, 2],
  "Russia": [0,0,2],
  "South Korea": [0, 3, 2],
  "Vietnam": [0, 2, 3],
  "Albania": [0,0,2],
  "Austria": [1, 2, 14],
  "Belgium": [0, 4, 1],
  "Bulgaria": [12, 15, 21],
  "Czech Republic": [1, 0, 0],
  "Denmark": [1, 0,0],
  "Estonia": [0, 2, 1],
  "France": [3, 7, 2],
  "Finland": [0, 2, 1],
  "Germany": [9, 14, 47],
  "Italy": [59, 89, 200],
  "Kosovo":[0,4, 0],
  "Latvia": [0,0,1],
  "Lithuania": [0,0,4],
  "Netherlands": [0, 2,4],
  "Poland": [2, 8, 6],
  "Portugal": [5, 1, 5],
  "Romania": [0, 2, 4],
  "Serbia":[0,3, 0],
  "Slovenia": [0, 2, 0],
  "Spain": [3, 6, 8],
  "Sweden": [1, 3, 1],
  "Switzerland": [0,0,3],
  "United Kingdom": [9, 32, 13],
  "Ukraine": [0, 1, 4],
  "Algeria": [0,0, 1],
  "Madagascar": [0,0, 3],
  "Marocco":[0,0,2],
  "New Zeland": [0, 2, 5]
}
